astroaugmentations/__init__.py
astroaugmentations/augmentations.py
astroaugmentations/datasets/MiraBest_F.py
astroaugmentations/datasets/__init__.py
astroaugmentations/datasets/galaxy_mnist.py
astroaugmentations/utils/__init__.py
astroaugmentations/utils/kernel_creation.py
datasets/MiraBest_F.py
datasets/__init__.py
datasets/galaxy_mnist.py
utils/__init__.py
utils/kernel_creation.py
AstroAugmentations-0.1.0.dist-info/LICENSE
AstroAugmentations-0.1.0.dist-info/METADATA
AstroAugmentations-0.1.0.dist-info/WHEEL
AstroAugmentations-0.1.0.dist-info/top_level.txt
AstroAugmentations-0.1.0.dist-info/RECORD
